markdown_extra/__init__.py
markdown_extra/meta.py
markdown_extra/resource_path.py
markdown_extra/summary.py
markdown_extra-1.0.1.dist-info/LICENSE.txt
markdown_extra-1.0.1.dist-info/METADATA
markdown_extra-1.0.1.dist-info/WHEEL
markdown_extra-1.0.1.dist-info/top_level.txt
markdown_extra-1.0.1.dist-info/RECORD
