Metadata-Version: 2.1
Name: markdown-extra
Version: 1.0.1
Summary: Set of extensions for markdown
Home-page: https://github.com/Nicals/markdown-extra
Author: Nicolas Appriou
Author-email: nicolas.appriou@gmail.com
License: MIT
Keywords: markdown yaml
Platform: UNKNOWN
Classifier: Development Status :: 5 - Production/Stable
Classifier: Intended Audience :: Developers
Classifier: License :: OSI Approved :: MIT License
Classifier: Programming Language :: Python :: 2
Classifier: Programming Language :: Python :: 3
Classifier: Topic :: Text Processing :: Markup :: HTML
Requires-Dist: markdown
Requires-Dist: pyYAML
Provides-Extra: docs
Requires-Dist: sphinx ; extra == 'docs'
Provides-Extra: tests
Requires-Dist: pytest ; extra == 'tests'
Requires-Dist: mock ; (python_version < "3.3") and extra == 'tests'
